idmbd/__init__.py
idmbd-0.2.dist-info/DESCRIPTION.rst
idmbd-0.2.dist-info/METADATA
idmbd-0.2.dist-info/RECORD
idmbd-0.2.dist-info/WHEEL
idmbd-0.2.dist-info/metadata.json
idmbd-0.2.dist-info/top_level.txt
