Metadata-Version: 2.0
Name: idmbd
Version: 0.2
Summary: Innovando el Desarrollo de Modelos a traves del Big Data
Home-page: http://github.com/cpazsantos/ciffmbd2016pldmcp
Author: Paola Lopez, Diego Martin, Carlos Paz
Author-email: cpazsantos@gmail.com
License: UNKNOWN
Platform: UNKNOWN
